[{"id":255009,"name":"K. Taylor","full":"Kenneth Ina Dorothea Taylor","pos":"MID","fifa_pos":["CM","CAM"],"ovr":78,"pot":84,"age":23,"nat":"Netherlands","club":"Ajax","cid":245,"league":"Eredivisie","lvl":1,"jersey":8,"val":22000000,"foot":"Left","wf":5,"sm":3,"rep":1,"h":182,"pace":73,"sho":77,"pas":78,"dri":78,"def":67,"phy":74,"img":"https://cdn.sofifa.net/players/255/009/26_120.png","tags":""},{"id":203483,"name":"D. Klaassen","full":"Davy Klaassen","pos":"MID","fifa_pos":["CM","CDM"],"ovr":77,"pot":77,"age":32,"nat":"Netherlands","club":"Ajax","cid":245,"league":"Eredivisie","lvl":1,"jersey":18,"val":8500000,"foot":"Right","wf":3,"sm":3,"rep":2,"h":179,"pace":47,"sho":78,"pas":73,"dri":73,"def":73,"phy":77,"img":"https://cdn.sofifa.net/players/203/483/26_120.png","tags":""},{"id":200260,"name":"S. Berghuis","full":"Steven Berghuis","pos":"ATT","fifa_pos":["RW","CAM","RM"],"ovr":78,"pot":78,"age":33,"nat":"Netherlands","club":"Ajax","cid":245,"league":"Eredivisie","lvl":1,"jersey":23,"val":9000000,"foot":"Left","wf":2,"sm":3,"rep":3,"h":182,"pace":71,"sho":77,"pas":82,"dri":77,"def":39,"phy":68,"img":"https://cdn.sofifa.net/players/200/260/26_120.png","tags":""},{"id":253399,"name":"O. Edvardsen","full":"Oliver Valaker Edvardsen","pos":"ATT","fifa_pos":["LW","RW","LM"],"ovr":73,"pot":74,"age":26,"nat":"Norway","club":"Ajax","cid":245,"league":"Eredivisie","lvl":1,"jersey":17,"val":3600000,"foot":"Right","wf":3,"sm":3,"rep":1,"h":175,"pace":84,"sho":68,"pas":64,"dri":76,"def":56,"phy":76,"img":"https://cdn.sofifa.net/players/253/399/26_120.png","tags":"Acrobat"},{"id":229158,"name":"B. van den Boomen","full":"Branco van den Boomen","pos":"MID","fifa_pos":["CM","CDM","CAM"],"ovr":73,"pot":73,"age":29,"nat":"Netherlands","club":"Ajax","cid":245,"league":"Eredivisie","lvl":1,"jersey":21,"val":3000000,"foot":"Right","wf":4,"sm":3,"rep":1,"h":188,"pace":39,"sho":73,"pas":81,"dri":67,"def":62,"phy":72,"img":"https://cdn.sofifa.net/players/229/158/26_120.png","tags":""},{"id":265390,"name":"Y. Regeer","full":"Youri Pieter Regeer","pos":"MID","fifa_pos":["CM","RB","CDM"],"ovr":73,"pot":83,"age":21,"nat":"Netherlands","club":"Ajax","cid":245,"league":"Eredivisie","lvl":1,"jersey":6,"val":7000000,"foot":"Right","wf":4,"sm":3,"rep":1,"h":177,"pace":75,"sho":61,"pas":72,"dri":74,"def":69,"phy":68,"img":"https://cdn.sofifa.net/players/265/390/26_120.png","tags":""},{"id":233152,"name":"K. Itakura","full":"Ko Itakura板倉 滉","pos":"DEF","fifa_pos":["CB","CDM"],"ovr":77,"pot":78,"age":28,"nat":"Japan","club":"Ajax","cid":245,"league":"Eredivisie","lvl":1,"jersey":4,"val":10000000,"foot":"Right","wf":4,"sm":3,"rep":2,"h":188,"pace":75,"sho":59,"pas":61,"dri":74,"def":77,"phy":76,"img":"https://cdn.sofifa.net/players/233/152/26_120.png","tags":""},{"id":262218,"name":"K. Fitz-Jim","full":"Kian Fitz-Jim","pos":"MID","fifa_pos":["CM","CAM"],"ovr":73,"pot":82,"age":21,"nat":"Netherlands","club":"Ajax","cid":245,"league":"Eredivisie","lvl":1,"jersey":28,"val":7000000,"foot":"Right","wf":3,"sm":3,"rep":1,"h":174,"pace":75,"sho":58,"pas":70,"dri":78,"def":66,"phy":62,"img":"https://cdn.sofifa.net/players/262/218/26_120.png","tags":""},{"id":223689,"name":"W. Weghorst","full":"Wout François Maria Weghorst","pos":"ATT","fifa_pos":["ST"],"ovr":78,"pot":78,"age":32,"nat":"Netherlands","club":"Ajax","cid":245,"league":"Eredivisie","lvl":1,"jersey":25,"val":11500000,"foot":"Right","wf":3,"sm":2,"rep":2,"h":197,"pace":54,"sho":78,"pas":62,"dri":68,"def":57,"phy":87,"img":"https://cdn.sofifa.net/players/223/689/26_120.png","tags":"Aerial threat, Strength"},{"id":236572,"name":"O. Wijndal","full":"Owen Colin Wijndal","pos":"DEF","fifa_pos":["LB","LM"],"ovr":72,"pot":76,"age":25,"nat":"Netherlands","club":"Ajax","cid":245,"league":"Eredivisie","lvl":1,"jersey":5,"val":3000000,"foot":"Left","wf":2,"sm":3,"rep":1,"h":176,"pace":78,"sho":54,"pas":70,"dri":71,"def":67,"phy":70,"img":"https://cdn.sofifa.net/players/236/572/26_120.png","tags":""},{"id":269153,"name":"A. Gaaei","full":"Anton Gaaei","pos":"DEF","fifa_pos":["RB","RM"],"ovr":72,"pot":79,"age":22,"nat":"Denmark","club":"Ajax","cid":245,"league":"Eredivisie","lvl":1,"jersey":3,"val":4500000,"foot":"Right","wf":3,"sm":2,"rep":1,"h":183,"pace":81,"sho":64,"pas":63,"dri":66,"def":64,"phy":74,"img":"https://cdn.sofifa.net/players/269/153/26_120.png","tags":""},{"id":228687,"name":"K. Dolberg","full":"Kasper Dolberg Rasmussen","pos":"ATT","fifa_pos":["ST"],"ovr":77,"pot":77,"age":27,"nat":"Denmark","club":"Ajax","cid":245,"league":"Eredivisie","lvl":1,"jersey":9,"val":11500000,"foot":"Right","wf":4,"sm":3,"rep":2,"h":187,"pace":73,"sho":80,"pas":66,"dri":73,"def":30,"phy":70,"img":"https://cdn.sofifa.net/players/228/687/26_120.png","tags":""},{"id":264220,"name":"Y. Baas","full":"Youri Baas","pos":"DEF","fifa_pos":["CB","LB"],"ovr":75,"pot":83,"age":22,"nat":"Netherlands","club":"Ajax","cid":245,"league":"Eredivisie","lvl":1,"jersey":15,"val":12000000,"foot":"Left","wf":2,"sm":2,"rep":1,"h":182,"pace":71,"sho":40,"pas":69,"dri":72,"def":76,"phy":71,"img":"https://cdn.sofifa.net/players/264/220/26_120.png","tags":""},{"id":258378,"name":"M. Godts","full":"Mika Marcel Godts","pos":"ATT","fifa_pos":["LW","LM"],"ovr":74,"pot":85,"age":20,"nat":"Belgium","club":"Ajax","cid":245,"league":"Eredivisie","lvl":1,"jersey":11,"val":9500000,"foot":"Right","wf":3,"sm":4,"rep":1,"h":176,"pace":81,"sho":64,"pas":68,"dri":81,"def":39,"phy":61,"img":"https://cdn.sofifa.net/players/258/378/26_120.png","tags":""},{"id":274288,"name":"O. Gloukh","full":"Oscar Gloukh","pos":"MID","fifa_pos":["CAM","LW","CM"],"ovr":76,"pot":85,"age":21,"nat":"Israel","club":"Ajax","cid":245,"league":"Eredivisie","lvl":1,"jersey":10,"val":17000000,"foot":"Right","wf":4,"sm":4,"rep":1,"h":171,"pace":82,"sho":70,"pas":71,"dri":82,"def":36,"phy":48,"img":"https://cdn.sofifa.net/players/274/288/26_120.png","tags":""},{"id":278292,"name":"J. McConnell","full":"James McConnell","pos":"MID","fifa_pos":["CDM","CM"],"ovr":68,"pot":79,"age":20,"nat":"England","club":"Ajax","cid":245,"league":"Eredivisie","lvl":1,"jersey":16,"val":2500000,"foot":"Right","wf":3,"sm":2,"rep":1,"h":180,"pace":64,"sho":57,"pas":68,"dri":67,"def":61,"phy":64,"img":"https://cdn.sofifa.net/players/278/292/26_120.png","tags":""},{"id":256325,"name":"J. Šutalo","full":"Josip Šutalo","pos":"DEF","fifa_pos":["CB"],"ovr":78,"pot":82,"age":25,"nat":"Croatia","club":"Ajax","cid":245,"league":"Eredivisie","lvl":1,"jersey":37,"val":17500000,"foot":"Right","wf":3,"sm":2,"rep":1,"h":185,"pace":77,"sho":32,"pas":62,"dri":72,"def":78,"phy":80,"img":"https://cdn.sofifa.net/players/256/325/26_120.png","tags":""},{"id":272357,"name":"Lucas Rosa","full":"Lucas Oliveira Rosa","pos":"DEF","fifa_pos":["RB","LB","RM"],"ovr":71,"pot":74,"age":25,"nat":"Brazil","club":"Ajax","cid":245,"league":"Eredivisie","lvl":1,"jersey":2,"val":2300000,"foot":"Right","wf":4,"sm":3,"rep":1,"h":176,"pace":74,"sho":42,"pas":61,"dri":66,"def":66,"phy":66,"img":"https://cdn.sofifa.net/players/272/357/26_120.png","tags":""},{"id":258139,"name":"Raúl Moro","full":"Raúl Moro Prescoli","pos":"ATT","fifa_pos":["LW","RW","LM"],"ovr":76,"pot":84,"age":22,"nat":"Spain","club":"Ajax","cid":245,"league":"Eredivisie","lvl":1,"jersey":7,"val":17000000,"foot":"Right","wf":3,"sm":3,"rep":1,"h":169,"pace":83,"sho":65,"pas":71,"dri":81,"def":27,"phy":49,"img":"https://cdn.sofifa.net/players/258/139/26_120.png","tags":""},{"id":71351,"name":"J. Mokio","full":"Jorthy Mokio","pos":"MID","fifa_pos":["CDM","CM","LB","CB"],"ovr":70,"pot":89,"age":17,"nat":"Belgium","club":"Ajax","cid":245,"league":"Eredivisie","lvl":1,"jersey":24,"val":3800000,"foot":"Left","wf":3,"sm":2,"rep":1,"h":182,"pace":70,"sho":51,"pas":64,"dri":72,"def":69,"phy":66,"img":"https://cdn.sofifa.net/players/071/351/26_120.png","tags":""},{"id":77152,"name":"S. Steur","full":"Sean Steur","pos":"MID","fifa_pos":["CM","CDM"],"ovr":64,"pot":83,"age":17,"nat":"Netherlands","club":"Ajax","cid":245,"league":"Eredivisie","lvl":1,"jersey":48,"val":1500000,"foot":"Right","wf":4,"sm":3,"rep":1,"h":183,"pace":72,"sho":52,"pas":65,"dri":71,"def":50,"phy":52,"img":"https://cdn.sofifa.net/players/077/152/26_120.png","tags":""},{"id":76116,"name":"A. Bouwman","full":"Aaron Bouwman","pos":"DEF","fifa_pos":["CB"],"ovr":65,"pot":83,"age":17,"nat":"Netherlands","club":"Ajax","cid":245,"league":"Eredivisie","lvl":1,"jersey":30,"val":1700000,"foot":"Right","wf":3,"sm":2,"rep":1,"h":188,"pace":64,"sho":50,"pas":53,"dri":57,"def":65,"phy":65,"img":"https://cdn.sofifa.net/players/076/116/26_120.png","tags":""},{"id":77814,"name":"L. Jetten","full":"Lucas Jetten","pos":"DEF","fifa_pos":["LB","LM"],"ovr":62,"pot":82,"age":18,"nat":"Netherlands","club":"Ajax","cid":245,"league":"Eredivisie","lvl":1,"jersey":46,"val":1100000,"foot":"Left","wf":3,"sm":2,"rep":1,"h":166,"pace":84,"sho":37,"pas":56,"dri":68,"def":55,"phy":52,"img":"https://cdn.sofifa.net/players/077/814/26_120.png","tags":""},{"id":76843,"name":"G. Alders","full":"Gerald Alders","pos":"DEF","fifa_pos":["RB","RM"],"ovr":61,"pot":78,"age":20,"nat":"Netherlands","club":"Ajax","cid":245,"league":"Eredivisie","lvl":1,"jersey":41,"val":825000,"foot":"Right","wf":3,"sm":2,"rep":1,"h":179,"pace":85,"sho":33,"pas":49,"dri":68,"def":55,"phy":59,"img":"https://cdn.sofifa.net/players/076/843/26_120.png","tags":""},{"id":76944,"name":"R. Bounida","full":"Rayane Bounida","pos":"ATT","fifa_pos":["LW","CAM","LM"],"ovr":64,"pot":84,"age":19,"nat":"Belgium","club":"Ajax","cid":245,"league":"Eredivisie","lvl":1,"jersey":43,"val":1600000,"foot":"Right","wf":4,"sm":4,"rep":1,"h":179,"pace":70,"sho":62,"pas":61,"dri":70,"def":30,"phy":36,"img":"https://cdn.sofifa.net/players/076/944/26_120.png","tags":""},{"id":75690,"name":"D. Konadu","full":"Don-Angelo Christoffel Annum-Assamoah Konadu","pos":"ATT","fifa_pos":["ST"],"ovr":63,"pot":82,"age":19,"nat":"Netherlands","club":"Ajax","cid":245,"league":"Eredivisie","lvl":1,"jersey":19,"val":1300000,"foot":"Right","wf":3,"sm":2,"rep":1,"h":190,"pace":73,"sho":60,"pas":48,"dri":63,"def":25,"phy":59,"img":"https://cdn.sofifa.net/players/075/690/26_120.png","tags":""},{"id":162328,"name":"R. Pasveer","full":"Remko Pasveer","pos":"GK","fifa_pos":["GK"],"ovr":75,"pot":75,"age":41,"nat":"Netherlands","club":"Ajax","cid":245,"league":"Eredivisie","lvl":1,"jersey":22,"val":625000,"foot":"Right","wf":4,"sm":1,"rep":1,"h":188,"pace":0,"sho":0,"pas":0,"dri":0,"def":0,"phy":0,"img":"https://cdn.sofifa.net/players/162/328/26_120.png","tags":""},{"id":253428,"name":"V. Jaroš","full":"Vítězslav Jaroš","pos":"GK","fifa_pos":["GK"],"ovr":70,"pot":78,"age":23,"nat":"Czechia","club":"Ajax","cid":245,"league":"Eredivisie","lvl":1,"jersey":1,"val":3100000,"foot":"Right","wf":3,"sm":1,"rep":1,"h":190,"pace":0,"sho":0,"pas":0,"dri":0,"def":0,"phy":0,"img":"https://cdn.sofifa.net/players/253/428/26_120.png","tags":""},{"id":80146,"name":"J. Heerkens","full":"Joeri Heerkens","pos":"GK","fifa_pos":["GK"],"ovr":64,"pot":80,"age":19,"nat":"Netherlands","club":"Ajax","cid":245,"league":"Eredivisie","lvl":1,"jersey":12,"val":1300000,"foot":"Right","wf":3,"sm":1,"rep":1,"h":193,"pace":0,"sho":0,"pas":0,"dri":0,"def":0,"phy":0,"img":"https://cdn.sofifa.net/players/080/146/26_120.png","tags":""},{"id":75816,"name":"P. Reverson","full":"Paul Peters Reverson","pos":"GK","fifa_pos":["GK"],"ovr":63,"pot":78,"age":20,"nat":"Ghana","club":"Ajax","cid":245,"league":"Eredivisie","lvl":1,"jersey":52,"val":1000000,"foot":"Right","wf":3,"sm":1,"rep":1,"h":194,"pace":0,"sho":0,"pas":0,"dri":0,"def":0,"phy":0,"img":"https://cdn.sofifa.net/players/075/816/26_120.png","tags":""}]