[{"id":237183,"name":"M. Rojas","full":"Matías Nicolás Rojas Romero","pos":"ATT","fifa_pos":["RW","CAM","RM"],"ovr":74,"pot":74,"age":29,"nat":"Paraguay","club":"Portland Timbers","cid":111140,"league":"Major League Soccer","lvl":1,"jersey":35,"val":4099999,"foot":"Left","wf":3,"sm":4,"rep":1,"h":180,"pace":70,"sho":77,"pas":74,"dri":77,"def":56,"phy":63,"img":"https://cdn.sofifa.net/players/237/183/26_120.png","tags":""},{"id":223816,"name":"J. Rodríguez","full":"Jonathan Javier Rodríguez Portillo","pos":"MID","fifa_pos":["LM","ST","LW"],"ovr":76,"pot":76,"age":31,"nat":"Uruguay","club":"Portland Timbers","cid":111140,"league":"Major League Soccer","lvl":1,"jersey":14,"val":6000000,"foot":"Right","wf":3,"sm":4,"rep":1,"h":177,"pace":85,"sho":76,"pas":67,"dri":77,"def":38,"phy":75,"img":"https://cdn.sofifa.net/players/223/816/26_120.png","tags":""},{"id":254887,"name":"J. Ortiz","full":"Julio Joao Ortiz Landázuri","pos":"MID","fifa_pos":["CDM","CM","CB"],"ovr":71,"pot":71,"age":29,"nat":"Ecuador","club":"Portland Timbers","cid":111140,"league":"Major League Soccer","lvl":1,"jersey":80,"val":1600000,"foot":"Right","wf":3,"sm":3,"rep":1,"h":177,"pace":72,"sho":68,"pas":67,"dri":71,"def":68,"phy":75,"img":"https://cdn.sofifa.net/players/254/887/26_120.png","tags":""},{"id":241004,"name":"F. Carballo","full":"Felipe Ignacio Carballo Ares","pos":"MID","fifa_pos":["CM","CDM","LM","CB"],"ovr":73,"pot":73,"age":28,"nat":"Uruguay","club":"Portland Timbers","cid":111140,"league":"Major League Soccer","lvl":1,"jersey":33,"val":3000000,"foot":"Right","wf":3,"sm":2,"rep":1,"h":177,"pace":69,"sho":68,"pas":70,"dri":72,"def":66,"phy":72,"img":"https://cdn.sofifa.net/players/241/004/26_120.png","tags":""},{"id":237203,"name":"C. Paredes","full":"Cristhian Fabián Paredes Maciel","pos":"MID","fifa_pos":["CDM","CM"],"ovr":67,"pot":67,"age":27,"nat":"Paraguay","club":"Portland Timbers","cid":111140,"league":"Major League Soccer","lvl":1,"jersey":17,"val":950000,"foot":"Right","wf":2,"sm":2,"rep":1,"h":183,"pace":66,"sho":63,"pas":63,"dri":64,"def":65,"phy":70,"img":"https://cdn.sofifa.net/players/237/203/26_120.png","tags":""},{"id":203067,"name":"D. Chará","full":"Diego Ferney Chará Zamora","pos":"MID","fifa_pos":["CDM","CM","CB"],"ovr":70,"pot":70,"age":39,"nat":"Colombia","club":"Portland Timbers","cid":111140,"league":"Major League Soccer","lvl":1,"jersey":21,"val":325000,"foot":"Right","wf":4,"sm":3,"rep":1,"h":172,"pace":68,"sho":52,"pas":61,"dri":67,"def":69,"phy":73,"img":"https://cdn.sofifa.net/players/203/067/26_120.png","tags":""},{"id":238303,"name":"K. Velde","full":"Kristoffer Velde","pos":"MID","fifa_pos":["LM","LW"],"ovr":70,"pot":71,"age":25,"nat":"Norway","club":"Portland Timbers","cid":111140,"league":"Major League Soccer","lvl":1,"jersey":99,"val":1900000,"foot":"Right","wf":2,"sm":4,"rep":1,"h":179,"pace":80,"sho":68,"pas":65,"dri":72,"def":43,"phy":63,"img":"https://cdn.sofifa.net/players/238/303/26_120.png","tags":""},{"id":259139,"name":"David da Costa","full":"David Pereira da Costa","pos":"MID","fifa_pos":["CAM","LW","CM"],"ovr":75,"pot":78,"age":24,"nat":"Portugal","club":"Portland Timbers","cid":111140,"league":"Major League Soccer","lvl":1,"jersey":10,"val":7500000,"foot":"Right","wf":4,"sm":3,"rep":1,"h":168,"pace":76,"sho":68,"pas":73,"dri":79,"def":34,"phy":47,"img":"https://cdn.sofifa.net/players/259/139/26_120.png","tags":""},{"id":247648,"name":"K. Miller","full":"Kamal Anthony Miller","pos":"DEF","fifa_pos":["CB"],"ovr":71,"pot":71,"age":28,"nat":"Canada","club":"Portland Timbers","cid":111140,"league":"Major League Soccer","lvl":1,"jersey":4,"val":1600000,"foot":"Left","wf":3,"sm":3,"rep":1,"h":183,"pace":75,"sho":48,"pas":59,"dri":63,"def":68,"phy":81,"img":"https://cdn.sofifa.net/players/247/648/26_120.png","tags":""},{"id":259111,"name":"J. Fory","full":"Jimer Esteban Fory Mejía","pos":"DEF","fifa_pos":["LB","LM","LW"],"ovr":69,"pot":76,"age":23,"nat":"Colombia","club":"Portland Timbers","cid":111140,"league":"Major League Soccer","lvl":1,"jersey":27,"val":2700000,"foot":"Left","wf":3,"sm":2,"rep":1,"h":187,"pace":75,"sho":50,"pas":63,"dri":67,"def":63,"phy":73,"img":"https://cdn.sofifa.net/players/259/111/26_120.png","tags":""},{"id":254578,"name":"D. Ayala","full":"Maximiliano David Ayala","pos":"MID","fifa_pos":["CDM","CM"],"ovr":69,"pot":75,"age":22,"nat":"Argentina","club":"Portland Timbers","cid":111140,"league":"Major League Soccer","lvl":1,"jersey":24,"val":2100000,"foot":"Left","wf":3,"sm":3,"rep":1,"h":173,"pace":70,"sho":53,"pas":62,"dri":69,"def":65,"phy":63,"img":"https://cdn.sofifa.net/players/254/578/26_120.png","tags":""},{"id":255894,"name":"J. Mosquera","full":"Juan David Mosquera López","pos":"DEF","fifa_pos":["RB","RM","RW"],"ovr":67,"pot":76,"age":22,"nat":"Colombia","club":"Portland Timbers","cid":111140,"league":"Major League Soccer","lvl":1,"jersey":29,"val":2200000,"foot":"Right","wf":3,"sm":3,"rep":1,"h":180,"pace":79,"sho":52,"pas":61,"dri":71,"def":58,"phy":72,"img":"https://cdn.sofifa.net/players/255/894/26_120.png","tags":""},{"id":263947,"name":"Antony","full":"Antony Alves Santos","pos":"MID","fifa_pos":["LM","RM","LW"],"ovr":71,"pot":75,"age":23,"nat":"Brazil","club":"Portland Timbers","cid":111140,"league":"Major League Soccer","lvl":1,"jersey":11,"val":2700000,"foot":"Right","wf":3,"sm":3,"rep":1,"h":178,"pace":89,"sho":59,"pas":64,"dri":72,"def":40,"phy":57,"img":"https://cdn.sofifa.net/players/263/947/26_120.png","tags":""},{"id":229881,"name":"A. Lassiter","full":"Ariel Daniel Lassiter Acuña","pos":"MID","fifa_pos":["LM","RM","ST","LB"],"ovr":66,"pot":66,"age":30,"nat":"Costa Rica","club":"Portland Timbers","cid":111140,"league":"Major League Soccer","lvl":1,"jersey":7,"val":825000,"foot":"Left","wf":5,"sm":3,"rep":1,"h":178,"pace":81,"sho":64,"pas":58,"dri":66,"def":38,"phy":59,"img":"https://cdn.sofifa.net/players/229/881/26_120.png","tags":""},{"id":213620,"name":"F. Mora","full":"Felipe Andrés Mora Aliaga","pos":"ATT","fifa_pos":["ST"],"ovr":71,"pot":71,"age":31,"nat":"Chile","club":"Portland Timbers","cid":111140,"league":"Major League Soccer","lvl":1,"jersey":9,"val":1600000,"foot":"Right","wf":3,"sm":3,"rep":1,"h":175,"pace":71,"sho":71,"pas":55,"dri":70,"def":26,"phy":61,"img":"https://cdn.sofifa.net/players/213/620/26_120.png","tags":""},{"id":247084,"name":"O. Fernandez","full":"Omir Guadalupe Fernandez Mosso","pos":"MID","fifa_pos":["LM","RM","CAM","LW"],"ovr":66,"pot":67,"age":26,"nat":"United States","club":"Portland Timbers","cid":111140,"league":"Major League Soccer","lvl":1,"jersey":22,"val":1000000,"foot":"Right","wf":3,"sm":4,"rep":1,"h":170,"pace":80,"sho":53,"pas":58,"dri":70,"def":44,"phy":56,"img":"https://cdn.sofifa.net/players/247/084/26_120.png","tags":""},{"id":268300,"name":"K. Kelsy","full":"Kevin Jesús Kelsy Genez","pos":"ATT","fifa_pos":["ST"],"ovr":68,"pot":81,"age":20,"nat":"Venezuela","club":"Portland Timbers","cid":111140,"league":"Major League Soccer","lvl":1,"jersey":19,"val":2900000,"foot":"Left","wf":4,"sm":3,"rep":1,"h":193,"pace":77,"sho":67,"pas":48,"dri":64,"def":27,"phy":67,"img":"https://cdn.sofifa.net/players/268/300/26_120.png","tags":""},{"id":221656,"name":"E. Miller","full":"Eric Miller","pos":"DEF","fifa_pos":["LB","RB","CB","LM"],"ovr":64,"pot":64,"age":32,"nat":"United States","club":"Portland Timbers","cid":111140,"league":"Major League Soccer","lvl":1,"jersey":15,"val":400000,"foot":"Right","wf":3,"sm":2,"rep":1,"h":183,"pace":66,"sho":37,"pas":52,"dri":58,"def":61,"phy":71,"img":"https://cdn.sofifa.net/players/221/656/26_120.png","tags":""},{"id":266150,"name":"F. Surman","full":"Finn Surman","pos":"DEF","fifa_pos":["CB"],"ovr":68,"pot":75,"age":21,"nat":"New Zealand","club":"Portland Timbers","cid":111140,"league":"Major League Soccer","lvl":1,"jersey":20,"val":2300000,"foot":"Right","wf":2,"sm":2,"rep":1,"h":190,"pace":65,"sho":33,"pas":49,"dri":55,"def":66,"phy":78,"img":"https://cdn.sofifa.net/players/266/150/26_120.png","tags":""},{"id":257067,"name":"Z. McGraw","full":"Zac McGraw","pos":"DEF","fifa_pos":["CB"],"ovr":65,"pot":66,"age":28,"nat":"Canada","club":"Portland Timbers","cid":111140,"league":"Major League Soccer","lvl":1,"jersey":18,"val":675000,"foot":"Right","wf":2,"sm":2,"rep":1,"h":193,"pace":52,"sho":41,"pas":53,"dri":51,"def":64,"phy":75,"img":"https://cdn.sofifa.net/players/257/067/26_120.png","tags":""},{"id":215823,"name":"D. Župarić","full":"Dario Župarić","pos":"DEF","fifa_pos":["CB"],"ovr":65,"pot":65,"age":33,"nat":"Croatia","club":"Portland Timbers","cid":111140,"league":"Major League Soccer","lvl":1,"jersey":13,"val":350000,"foot":"Right","wf":4,"sm":2,"rep":1,"h":185,"pace":41,"sho":22,"pas":45,"dri":52,"def":64,"phy":74,"img":"https://cdn.sofifa.net/players/215/823/26_120.png","tags":""},{"id":77660,"name":"I. Smith","full":"Ian Smith","pos":"DEF","fifa_pos":["CB"],"ovr":54,"pot":63,"age":22,"nat":"United States","club":"Portland Timbers","cid":111140,"league":"Major League Soccer","lvl":1,"jersey":23,"val":230000,"foot":"Left","wf":3,"sm":2,"rep":1,"h":185,"pace":56,"sho":37,"pas":44,"dri":47,"def":55,"phy":57,"img":"https://cdn.sofifa.net/players/077/660/26_120.png","tags":""},{"id":79895,"name":"G. Guerra","full":"Gage Guerra","pos":"ATT","fifa_pos":["ST"],"ovr":54,"pot":62,"age":22,"nat":"United States","club":"Portland Timbers","cid":111140,"league":"Major League Soccer","lvl":1,"jersey":88,"val":240000,"foot":"Right","wf":3,"sm":2,"rep":1,"h":178,"pace":59,"sho":55,"pas":38,"dri":51,"def":23,"phy":55,"img":"https://cdn.sofifa.net/players/079/895/26_120.png","tags":""},{"id":213536,"name":"M. Crépeau","full":"Maxime Crépeau","pos":"GK","fifa_pos":["GK"],"ovr":69,"pot":69,"age":31,"nat":"Canada","club":"Portland Timbers","cid":111140,"league":"Major League Soccer","lvl":1,"jersey":16,"val":750000,"foot":"Right","wf":2,"sm":1,"rep":1,"h":180,"pace":0,"sho":0,"pas":0,"dri":0,"def":0,"phy":0,"img":"https://cdn.sofifa.net/players/213/536/26_120.png","tags":""},{"id":238919,"name":"J. Pantemis","full":"James PantemisΤζέιμς Παντέμης","pos":"GK","fifa_pos":["GK"],"ovr":65,"pot":66,"age":28,"nat":"Canada","club":"Portland Timbers","cid":111140,"league":"Major League Soccer","lvl":1,"jersey":41,"val":575000,"foot":"Left","wf":1,"sm":1,"rep":1,"h":188,"pace":0,"sho":0,"pas":0,"dri":0,"def":0,"phy":0,"img":"https://cdn.sofifa.net/players/238/919/26_120.png","tags":""},{"id":247346,"name":"T. Muse","full":"John David Muse III","pos":"GK","fifa_pos":["GK"],"ovr":54,"pot":58,"age":25,"nat":"United States","club":"Portland Timbers","cid":111140,"league":"Major League Soccer","lvl":1,"jersey":25,"val":120000,"foot":"Right","wf":1,"sm":1,"rep":1,"h":193,"pace":0,"sho":0,"pas":0,"dri":0,"def":0,"phy":0,"img":"https://cdn.sofifa.net/players/247/346/26_120.png","tags":""}]