[{"id":211504,"name":"L. Baker","full":"Lewis Renard Baker","pos":"MID","fifa_pos":["CM","CDM","CAM"],"ovr":70,"pot":70,"age":30,"nat":"England","club":"Stoke City","cid":1806,"league":"Championship","lvl":2,"jersey":8,"val":1500000,"foot":"Right","wf":5,"sm":3,"rep":1,"h":182,"pace":64,"sho":71,"pas":73,"dri":70,"def":64,"phy":71,"img":"https://cdn.sofifa.net/players/211/504/26_120.png","tags":""},{"id":258093,"name":"M. Manhoef","full":"Million Manhoef","pos":"MID","fifa_pos":["RM","RW"],"ovr":72,"pot":78,"age":23,"nat":"Netherlands","club":"Stoke City","cid":1806,"league":"Championship","lvl":2,"jersey":42,"val":3700000,"foot":"Left","wf":3,"sm":3,"rep":1,"h":170,"pace":85,"sho":67,"pas":63,"dri":73,"def":56,"phy":75,"img":"https://cdn.sofifa.net/players/258/093/26_120.png","tags":""},{"id":189615,"name":"A. Cresswell","full":"Aaron Cresswell","pos":"DEF","fifa_pos":["CB","LB","LM"],"ovr":73,"pot":73,"age":35,"nat":"England","club":"Stoke City","cid":1806,"league":"Championship","lvl":2,"jersey":3,"val":800000,"foot":"Left","wf":3,"sm":2,"rep":1,"h":175,"pace":50,"sho":59,"pas":73,"dri":71,"def":75,"phy":62,"img":"https://cdn.sofifa.net/players/189/615/26_120.png","tags":""},{"id":260478,"name":"S. Thomas","full":"Benjamin Sorba William Thomas","pos":"MID","fifa_pos":["RM","LM","ST","RW"],"ovr":71,"pot":72,"age":26,"nat":"Wales","club":"Stoke City","cid":1806,"league":"Championship","lvl":2,"jersey":7,"val":2200000,"foot":"Right","wf":2,"sm":3,"rep":1,"h":185,"pace":87,"sho":59,"pas":67,"dri":70,"def":48,"phy":70,"img":"https://cdn.sofifa.net/players/260/478/26_120.png","tags":""},{"id":72557,"name":"T. Rigo","full":"Tomáš Rigo","pos":"MID","fifa_pos":["CM","CAM","CDM"],"ovr":70,"pot":75,"age":23,"nat":"Slovakia","club":"Stoke City","cid":1806,"league":"Championship","lvl":2,"jersey":19,"val":2400000,"foot":"Right","wf":3,"sm":3,"rep":1,"h":184,"pace":65,"sho":63,"pas":69,"dri":68,"def":65,"phy":67,"img":"https://cdn.sofifa.net/players/072/557/26_120.png","tags":""},{"id":277835,"name":"B. Lawal","full":"Mohammed Bosun Lawal","pos":"MID","fifa_pos":["CM","CB","RB","RM"],"ovr":65,"pot":76,"age":22,"nat":"Republic of Ireland","club":"Stoke City","cid":1806,"league":"Championship","lvl":2,"jersey":18,"val":1600000,"foot":"Right","wf":4,"sm":2,"rep":1,"h":188,"pace":71,"sho":60,"pas":64,"dri":63,"def":64,"phy":79,"img":"https://cdn.sofifa.net/players/277/835/26_120.png","tags":""},{"id":255446,"name":"É. Bocat","full":"Eric-Junior Bocat","pos":"DEF","fifa_pos":["LB","LM"],"ovr":69,"pot":72,"age":25,"nat":"France","club":"Stoke City","cid":1806,"league":"Championship","lvl":2,"jersey":17,"val":1700000,"foot":"Left","wf":3,"sm":2,"rep":1,"h":182,"pace":78,"sho":52,"pas":65,"dri":68,"def":62,"phy":67,"img":"https://cdn.sofifa.net/players/255/446/26_120.png","tags":""},{"id":255590,"name":"T. Seko","full":"Tatsuki Seko瀬古 樹","pos":"MID","fifa_pos":["CDM","CM"],"ovr":68,"pot":69,"age":27,"nat":"Japan","club":"Stoke City","cid":1806,"league":"Championship","lvl":2,"jersey":12,"val":1200000,"foot":"Right","wf":3,"sm":2,"rep":1,"h":175,"pace":65,"sho":54,"pas":69,"dri":68,"def":63,"phy":67,"img":"https://cdn.sofifa.net/players/255/590/26_120.png","tags":""},{"id":259869,"name":"J. Tchamadeu","full":"Junior Baptiste Tchamadeu","pos":"DEF","fifa_pos":["RB","RM"],"ovr":68,"pot":76,"age":21,"nat":"Cameroon","club":"Stoke City","cid":1806,"league":"Championship","lvl":2,"jersey":22,"val":2600000,"foot":"Right","wf":3,"sm":2,"rep":1,"h":180,"pace":82,"sho":54,"pas":60,"dri":67,"def":61,"phy":72,"img":"https://cdn.sofifa.net/players/259/869/26_120.png","tags":""},{"id":255409,"name":"R. Boženík","full":"Róbert Boženík","pos":"ATT","fifa_pos":["ST"],"ovr":70,"pot":75,"age":25,"nat":"Slovakia","club":"Stoke City","cid":1806,"league":"Championship","lvl":2,"jersey":11,"val":2400000,"foot":"Right","wf":4,"sm":3,"rep":1,"h":188,"pace":75,"sho":71,"pas":63,"dri":67,"def":34,"phy":74,"img":"https://cdn.sofifa.net/players/255/409/26_120.png","tags":""},{"id":187936,"name":"S. Nzonzi","full":"Steven N'Kemboanza Mike Christopher Nzonzi","pos":"MID","fifa_pos":["CDM","CM"],"ovr":72,"pot":72,"age":36,"nat":"France","club":"Stoke City","cid":1806,"league":"Championship","lvl":2,"jersey":15,"val":450000,"foot":"Right","wf":3,"sm":2,"rep":1,"h":196,"pace":37,"sho":56,"pas":67,"dri":66,"def":72,"phy":76,"img":"https://cdn.sofifa.net/players/187/936/26_120.png","tags":"Aerial threat, Strength"},{"id":213905,"name":"S. Gallagher","full":"Samuel James Gallagher","pos":"ATT","fifa_pos":["ST"],"ovr":69,"pot":69,"age":29,"nat":"England","club":"Stoke City","cid":1806,"league":"Championship","lvl":2,"jersey":20,"val":1400000,"foot":"Right","wf":3,"sm":3,"rep":1,"h":193,"pace":66,"sho":70,"pas":57,"dri":64,"def":45,"phy":78,"img":"https://cdn.sofifa.net/players/213/905/26_120.png","tags":""},{"id":213689,"name":"B. Pearson","full":"Benjamin David Pearson","pos":"MID","fifa_pos":["CDM","CM"],"ovr":70,"pot":70,"age":30,"nat":"England","club":"Stoke City","cid":1806,"league":"Championship","lvl":2,"jersey":4,"val":1300000,"foot":"Right","wf":3,"sm":3,"rep":1,"h":176,"pace":55,"sho":49,"pas":62,"dri":67,"def":67,"phy":76,"img":"https://cdn.sofifa.net/players/213/689/26_120.png","tags":""},{"id":266774,"name":"Bae Jun Ho","full":"Jun-ho Bae배준호","pos":"MID","fifa_pos":["LM","CAM","LW"],"ovr":71,"pot":80,"age":21,"nat":"Korea Republic","club":"Stoke City","cid":1806,"league":"Championship","lvl":2,"jersey":10,"val":4200000,"foot":"Right","wf":4,"sm":3,"rep":1,"h":178,"pace":74,"sho":61,"pas":69,"dri":73,"def":36,"phy":55,"img":"https://cdn.sofifa.net/players/266/774/26_120.png","tags":""},{"id":262082,"name":"L. Cissé","full":"Mohamed Lamine Cissé","pos":"ATT","fifa_pos":["ST","RM","LM","RW"],"ovr":68,"pot":78,"age":22,"nat":"France","club":"Stoke City","cid":1806,"league":"Championship","lvl":2,"jersey":29,"val":2700000,"foot":"Right","wf":3,"sm":3,"rep":1,"h":179,"pace":81,"sho":67,"pas":61,"dri":72,"def":27,"phy":59,"img":"https://cdn.sofifa.net/players/262/082/26_120.png","tags":""},{"id":243401,"name":"André Vidigal","full":"André Filipe Cunha Vidigal","pos":"MID","fifa_pos":["LM","ST","LW"],"ovr":68,"pot":68,"age":26,"nat":"Angola","club":"Stoke City","cid":1806,"league":"Championship","lvl":2,"jersey":27,"val":1300000,"foot":"Right","wf":4,"sm":4,"rep":1,"h":176,"pace":85,"sho":63,"pas":60,"dri":71,"def":28,"phy":59,"img":"https://cdn.sofifa.net/players/243/401/26_120.png","tags":""},{"id":278557,"name":"J. Donley","full":"Jamie Paul Donley","pos":"MID","fifa_pos":["CAM","CM"],"ovr":67,"pot":81,"age":20,"nat":"Northern Ireland","club":"Stoke City","cid":1806,"league":"Championship","lvl":2,"jersey":14,"val":2500000,"foot":"Left","wf":3,"sm":3,"rep":1,"h":183,"pace":66,"sho":62,"pas":66,"dri":67,"def":37,"phy":61,"img":"https://cdn.sofifa.net/players/278/557/26_120.png","tags":""},{"id":264731,"name":"A. Phillips","full":"Ashley Phillips","pos":"DEF","fifa_pos":["CB"],"ovr":70,"pot":81,"age":20,"nat":"England","club":"Stoke City","cid":1806,"league":"Championship","lvl":2,"jersey":26,"val":3300000,"foot":"Right","wf":3,"sm":2,"rep":1,"h":192,"pace":65,"sho":40,"pas":56,"dri":59,"def":70,"phy":75,"img":"https://cdn.sofifa.net/players/264/731/26_120.png","tags":""},{"id":238389,"name":"B. Wilmot","full":"Benjamin Lewis Wilmot","pos":"DEF","fifa_pos":["CB","RB"],"ovr":69,"pot":73,"age":25,"nat":"England","club":"Stoke City","cid":1806,"league":"Championship","lvl":2,"jersey":16,"val":1700000,"foot":"Right","wf":3,"sm":2,"rep":1,"h":188,"pace":52,"sho":39,"pas":55,"dri":59,"def":70,"phy":72,"img":"https://cdn.sofifa.net/players/238/389/26_120.png","tags":""},{"id":266180,"name":"M. Talovierov","full":"Maksym Vadymovych TalovierovТаловєров Максим Вадимович","pos":"DEF","fifa_pos":["CB"],"ovr":69,"pot":74,"age":25,"nat":"Ukraine","club":"Stoke City","cid":1806,"league":"Championship","lvl":2,"jersey":40,"val":1800000,"foot":"Right","wf":3,"sm":2,"rep":1,"h":195,"pace":61,"sho":38,"pas":51,"dri":56,"def":68,"phy":78,"img":"https://cdn.sofifa.net/players/266/180/26_120.png","tags":""},{"id":271227,"name":"D. Mubama","full":"Divin Mubama","pos":"ATT","fifa_pos":["ST"],"ovr":63,"pot":78,"age":20,"nat":"England","club":"Stoke City","cid":1806,"league":"Championship","lvl":2,"jersey":9,"val":1200000,"foot":"Left","wf":3,"sm":2,"rep":1,"h":183,"pace":72,"sho":62,"pas":47,"dri":61,"def":27,"phy":60,"img":"https://cdn.sofifa.net/players/271/227/26_120.png","tags":""},{"id":200408,"name":"B. Gibson","full":"Benjamin James Gibson","pos":"DEF","fifa_pos":["CB"],"ovr":68,"pot":68,"age":32,"nat":"England","club":"Stoke City","cid":1806,"league":"Championship","lvl":2,"jersey":23,"val":775000,"foot":"Left","wf":3,"sm":2,"rep":1,"h":185,"pace":43,"sho":28,"pas":48,"dri":46,"def":69,"phy":74,"img":"https://cdn.sofifa.net/players/200/408/26_120.png","tags":""},{"id":278828,"name":"J. Dixon","full":"Jaden Dixon","pos":"DEF","fifa_pos":["CB","RB"],"ovr":56,"pot":76,"age":18,"nat":"England","club":"Stoke City","cid":1806,"league":"Championship","lvl":2,"jersey":41,"val":375000,"foot":"Right","wf":3,"sm":2,"rep":1,"h":180,"pace":67,"sho":31,"pas":43,"dri":49,"def":54,"phy":61,"img":"https://cdn.sofifa.net/players/278/828/26_120.png","tags":""},{"id":77599,"name":"F. Fawunmi","full":"Favour Ayobamide Daniel Fawunmi","pos":"MID","fifa_pos":["RM","RW"],"ovr":56,"pot":72,"age":19,"nat":"England","club":"Stoke City","cid":1806,"league":"Championship","lvl":2,"jersey":56,"val":375000,"foot":"Left","wf":3,"sm":3,"rep":1,"h":180,"pace":70,"sho":52,"pas":51,"dri":59,"def":25,"phy":42,"img":"https://cdn.sofifa.net/players/077/599/26_120.png","tags":""},{"id":202125,"name":"J. Bonham","full":"Jack Elliott Bonham","pos":"GK","fifa_pos":["GK"],"ovr":65,"pot":65,"age":31,"nat":"Republic of Ireland","club":"Stoke City","cid":1806,"league":"Championship","lvl":2,"jersey":13,"val":375000,"foot":"Right","wf":3,"sm":1,"rep":1,"h":192,"pace":0,"sho":0,"pas":0,"dri":0,"def":0,"phy":0,"img":"https://cdn.sofifa.net/players/202/125/26_120.png","tags":""},{"id":169493,"name":"F. Fielding","full":"Francis David Fielding","pos":"GK","fifa_pos":["GK"],"ovr":63,"pot":63,"age":37,"nat":"England","club":"Stoke City","cid":1806,"league":"Championship","lvl":2,"jersey":34,"val":50000,"foot":"Right","wf":3,"sm":1,"rep":1,"h":180,"pace":0,"sho":0,"pas":0,"dri":0,"def":0,"phy":0,"img":"https://cdn.sofifa.net/players/169/493/26_120.png","tags":""},{"id":241643,"name":"V. Johansson","full":"Viktor Tobias Johansson","pos":"GK","fifa_pos":["GK"],"ovr":74,"pot":76,"age":26,"nat":"Sweden","club":"Stoke City","cid":1806,"league":"Championship","lvl":2,"jersey":1,"val":4000000,"foot":"Right","wf":3,"sm":1,"rep":1,"h":186,"pace":0,"sho":0,"pas":0,"dri":0,"def":0,"phy":0,"img":"https://cdn.sofifa.net/players/241/643/26_120.png","tags":""},{"id":80874,"name":"T. Grant","full":"True Grant","pos":"GK","fifa_pos":["GK"],"ovr":59,"pot":73,"age":19,"nat":"England","club":"Stoke City","cid":1806,"league":"Championship","lvl":2,"jersey":33,"val":475000,"foot":"Right","wf":2,"sm":1,"rep":1,"h":188,"pace":0,"sho":0,"pas":0,"dri":0,"def":0,"phy":0,"img":"https://cdn.sofifa.net/players/080/874/26_120.png","tags":""}]