[{"id":247166,"name":"J. Olayinka","full":"Olujimi James Olayinka","pos":"MID","fifa_pos":["CM","CDM","CAM"],"ovr":59,"pot":61,"age":24,"nat":"England","club":"Waterford FC","cid":753,"league":"Premier Division","lvl":1,"jersey":8,"val":300000,"foot":"Right","wf":4,"sm":3,"rep":1,"h":175,"pace":73,"sho":55,"pas":58,"dri":66,"def":56,"phy":52,"img":"https://cdn.sofifa.net/players/247/166/26_120.png","tags":""},{"id":233375,"name":"D. Leahy","full":"Darragh John Leahy","pos":"DEF","fifa_pos":["CB"],"ovr":60,"pot":60,"age":27,"nat":"Republic of Ireland","club":"Waterford FC","cid":753,"league":"Premier Division","lvl":1,"jersey":15,"val":230000,"foot":"Left","wf":3,"sm":2,"rep":1,"h":177,"pace":63,"sho":50,"pas":55,"dri":56,"def":58,"phy":70,"img":"https://cdn.sofifa.net/players/233/375/26_120.png","tags":""},{"id":261876,"name":"C. Noonan","full":"Conan Noonan","pos":"MID","fifa_pos":["CAM","RM","CM"],"ovr":61,"pot":66,"age":22,"nat":"Republic of Ireland","club":"Waterford FC","cid":753,"league":"Premier Division","lvl":1,"jersey":20,"val":500000,"foot":"Right","wf":4,"sm":3,"rep":1,"h":180,"pace":65,"sho":54,"pas":62,"dri":61,"def":50,"phy":52,"img":"https://cdn.sofifa.net/players/261/876/26_120.png","tags":""},{"id":221358,"name":"J. Rossiter","full":"Jordan Bernard Rossiter","pos":"MID","fifa_pos":["CM","CDM"],"ovr":58,"pot":58,"age":28,"nat":"England","club":"Waterford FC","cid":753,"league":"Premier Division","lvl":1,"jersey":24,"val":200000,"foot":"Right","wf":3,"sm":2,"rep":1,"h":178,"pace":50,"sho":50,"pas":55,"dri":58,"def":57,"phy":68,"img":"https://cdn.sofifa.net/players/221/358/26_120.png","tags":""},{"id":71148,"name":"D. McMenamy","full":"Dean McMenamy","pos":"MID","fifa_pos":["CM","CAM","CDM"],"ovr":57,"pot":60,"age":23,"nat":"Republic of Ireland","club":"Waterford FC","cid":753,"league":"Premier Division","lvl":1,"jersey":27,"val":220000,"foot":"Right","wf":3,"sm":2,"rep":1,"h":173,"pace":65,"sho":52,"pas":54,"dri":58,"def":54,"phy":51,"img":"https://cdn.sofifa.net/players/071/148/26_120.png","tags":""},{"id":272401,"name":"S. Glenfield","full":"Samuel Che Glenfield","pos":"MID","fifa_pos":["CM","CAM"],"ovr":56,"pot":62,"age":20,"nat":"Northern Ireland","club":"Waterford FC","cid":753,"league":"Premier Division","lvl":1,"jersey":19,"val":220000,"foot":"Right","wf":2,"sm":2,"rep":1,"h":180,"pace":66,"sho":52,"pas":51,"dri":59,"def":58,"phy":51,"img":"https://cdn.sofifa.net/players/272/401/26_120.png","tags":""},{"id":183807,"name":"P. Amond","full":"Pádraig Amond","pos":"ATT","fifa_pos":["ST"],"ovr":63,"pot":63,"age":37,"nat":"Republic of Ireland","club":"Waterford FC","cid":753,"league":"Premier Division","lvl":1,"jersey":9,"val":160000,"foot":"Right","wf":4,"sm":2,"rep":1,"h":178,"pace":33,"sho":65,"pas":52,"dri":61,"def":34,"phy":68,"img":"https://cdn.sofifa.net/players/183/807/26_120.png","tags":""},{"id":233950,"name":"M. Smith","full":"Matthew Smith","pos":"ATT","fifa_pos":["ST","CAM","LW"],"ovr":57,"pot":57,"age":28,"nat":"Scotland","club":"Waterford FC","cid":753,"league":"Premier Division","lvl":1,"jersey":10,"val":170000,"foot":"Right","wf":3,"sm":3,"rep":1,"h":180,"pace":68,"sho":57,"pas":49,"dri":58,"def":36,"phy":60,"img":"https://cdn.sofifa.net/players/233/950/26_120.png","tags":""},{"id":276927,"name":"K. White","full":"Kyle Richard White","pos":"MID","fifa_pos":["CM","LB","CAM"],"ovr":55,"pot":65,"age":21,"nat":"England","club":"Waterford FC","cid":753,"league":"Premier Division","lvl":1,"jersey":16,"val":275000,"foot":"Left","wf":2,"sm":2,"rep":1,"h":183,"pace":65,"sho":50,"pas":51,"dri":57,"def":51,"phy":60,"img":"https://cdn.sofifa.net/players/276/927/26_120.png","tags":""},{"id":251283,"name":"R. Burke","full":"Ryan Darren Burke","pos":"DEF","fifa_pos":["LB","CB","LM"],"ovr":59,"pot":60,"age":24,"nat":"Republic of Ireland","club":"Waterford FC","cid":753,"league":"Premier Division","lvl":1,"jersey":3,"val":250000,"foot":"Left","wf":2,"sm":2,"rep":1,"h":177,"pace":61,"sho":42,"pas":55,"dri":55,"def":55,"phy":60,"img":"https://cdn.sofifa.net/players/251/283/26_120.png","tags":""},{"id":239353,"name":"N. Bakboord","full":"Navajo Marcelino Bakboord","pos":"DEF","fifa_pos":["RB"],"ovr":58,"pot":58,"age":26,"nat":"Suriname","club":"Waterford FC","cid":753,"league":"Premier Division","lvl":1,"jersey":2,"val":200000,"foot":"Right","wf":2,"sm":2,"rep":1,"h":177,"pace":72,"sho":40,"pas":52,"dri":58,"def":52,"phy":61,"img":"https://cdn.sofifa.net/players/239/353/26_120.png","tags":""},{"id":262651,"name":"T. Lonergan","full":"Tom Lonergan","pos":"ATT","fifa_pos":["ST"],"ovr":60,"pot":65,"age":21,"nat":"Republic of Ireland","club":"Waterford FC","cid":753,"league":"Premier Division","lvl":1,"jersey":18,"val":375000,"foot":"Right","wf":3,"sm":2,"rep":1,"h":183,"pace":66,"sho":60,"pas":48,"dri":60,"def":21,"phy":61,"img":"https://cdn.sofifa.net/players/262/651/26_120.png","tags":""},{"id":274451,"name":"J. Dempsey","full":"Jesse Dempsey","pos":"DEF","fifa_pos":["LB","LM"],"ovr":57,"pot":63,"age":20,"nat":"Republic of Ireland","club":"Waterford FC","cid":753,"league":"Premier Division","lvl":1,"jersey":14,"val":240000,"foot":"Left","wf":3,"sm":2,"rep":1,"h":175,"pace":65,"sho":40,"pas":51,"dri":53,"def":52,"phy":55,"img":"https://cdn.sofifa.net/players/274/451/26_120.png","tags":""},{"id":255912,"name":"M. Faal","full":"Muhammadu Mustapha Faal","pos":"ATT","fifa_pos":["ST"],"ovr":58,"pot":58,"age":28,"nat":"England","club":"Waterford FC","cid":753,"league":"Premier Division","lvl":1,"jersey":7,"val":210000,"foot":"Right","wf":3,"sm":2,"rep":1,"h":196,"pace":70,"sho":57,"pas":46,"dri":56,"def":21,"phy":66,"img":"https://cdn.sofifa.net/players/255/912/26_120.png","tags":""},{"id":243910,"name":"T. Coyle","full":"Trae Bailey Coyle","pos":"MID","fifa_pos":["LM","LW","RM"],"ovr":58,"pot":64,"age":24,"nat":"England","club":"Waterford FC","cid":753,"league":"Premier Division","lvl":1,"jersey":99,"val":325000,"foot":"Right","wf":3,"sm":3,"rep":1,"h":179,"pace":74,"sho":52,"pas":54,"dri":59,"def":21,"phy":57,"img":"https://cdn.sofifa.net/players/243/910/26_120.png","tags":""},{"id":278183,"name":"F. Armstrong","full":"Finlay Patric Armstrong","pos":"DEF","fifa_pos":["LB","LM"],"ovr":57,"pot":61,"age":22,"nat":"England","club":"Waterford FC","cid":753,"league":"Premier Division","lvl":1,"jersey":23,"val":220000,"foot":"Left","wf":2,"sm":2,"rep":1,"h":183,"pace":71,"sho":33,"pas":46,"dri":50,"def":52,"phy":59,"img":"https://cdn.sofifa.net/players/278/183/26_120.png","tags":""},{"id":252835,"name":"G. Horton","full":"Grant Dean Horton","pos":"DEF","fifa_pos":["RB","CB","RM"],"ovr":58,"pot":60,"age":23,"nat":"England","club":"Waterford FC","cid":753,"league":"Premier Division","lvl":1,"jersey":5,"val":240000,"foot":"Right","wf":2,"sm":2,"rep":1,"h":192,"pace":49,"sho":36,"pas":50,"dri":50,"def":58,"phy":69,"img":"https://cdn.sofifa.net/players/252/835/26_120.png","tags":""},{"id":248770,"name":"K. Radkowski","full":"Kacper Radkowski","pos":"DEF","fifa_pos":["CB"],"ovr":58,"pot":60,"age":24,"nat":"Poland","club":"Waterford FC","cid":753,"league":"Premier Division","lvl":1,"jersey":17,"val":230000,"foot":"Right","wf":3,"sm":2,"rep":1,"h":194,"pace":51,"sho":33,"pas":47,"dri":48,"def":56,"phy":68,"img":"https://cdn.sofifa.net/players/248/770/26_120.png","tags":""},{"id":79680,"name":"J. Miles","full":"Josh Miles","pos":"MID","fifa_pos":["LM","LW"],"ovr":55,"pot":64,"age":18,"nat":"England","club":"Waterford FC","cid":753,"league":"Premier Division","lvl":1,"jersey":21,"val":275000,"foot":"Left","wf":3,"sm":2,"rep":1,"h":174,"pace":68,"sho":48,"pas":49,"dri":57,"def":29,"phy":43,"img":"https://cdn.sofifa.net/players/079/680/26_120.png","tags":""},{"id":199010,"name":"A. Boyle","full":"Andrew Boyle","pos":"DEF","fifa_pos":["CB"],"ovr":58,"pot":58,"age":34,"nat":"Republic of Ireland","club":"Waterford FC","cid":753,"league":"Premier Division","lvl":1,"jersey":4,"val":70000,"foot":"Right","wf":2,"sm":2,"rep":1,"h":185,"pace":33,"sho":37,"pas":47,"dri":39,"def":57,"phy":59,"img":"https://cdn.sofifa.net/players/199/010/26_120.png","tags":""},{"id":71149,"name":"A. Queally","full":"Adam Queally","pos":"DEF","fifa_pos":["CB"],"ovr":52,"pot":62,"age":19,"nat":"Republic of Ireland","club":"Waterford FC","cid":753,"league":"Premier Division","lvl":1,"jersey":26,"val":160000,"foot":"Right","wf":3,"sm":2,"rep":1,"h":183,"pace":52,"sho":35,"pas":40,"dri":40,"def":52,"phy":60,"img":"https://cdn.sofifa.net/players/071/149/26_120.png","tags":""},{"id":78231,"name":"R. Mansfield","full":"Ronan Mansfield","pos":"DEF","fifa_pos":["CB"],"ovr":55,"pot":63,"age":19,"nat":"Republic of Ireland","club":"Waterford FC","cid":753,"league":"Premier Division","lvl":1,"jersey":22,"val":250000,"foot":"Left","wf":2,"sm":2,"rep":1,"h":190,"pace":49,"sho":31,"pas":38,"dri":37,"def":53,"phy":64,"img":"https://cdn.sofifa.net/players/078/231/26_120.png","tags":""},{"id":77598,"name":"S. Keane","full":"Sean Keane","pos":"DEF","fifa_pos":["CB","CDM"],"ovr":53,"pot":60,"age":19,"nat":"Republic of Ireland","club":"Waterford FC","cid":753,"league":"Premier Division","lvl":1,"jersey":47,"val":170000,"foot":"Right","wf":2,"sm":2,"rep":1,"h":186,"pace":53,"sho":29,"pas":40,"dri":43,"def":53,"phy":61,"img":"https://cdn.sofifa.net/players/077/598/26_120.png","tags":""},{"id":77510,"name":"A. Zborowski","full":"Alan Zborowski","pos":"DEF","fifa_pos":["CB"],"ovr":52,"pot":62,"age":17,"nat":"Poland","club":"Waterford FC","cid":753,"league":"Premier Division","lvl":1,"jersey":43,"val":150000,"foot":"Right","wf":3,"sm":2,"rep":1,"h":187,"pace":51,"sho":24,"pas":32,"dri":35,"def":52,"phy":61,"img":"https://cdn.sofifa.net/players/077/510/26_120.png","tags":""},{"id":77509,"name":"N. O'Brien","full":"Noah O'Brien","pos":"DEF","fifa_pos":["CB"],"ovr":51,"pot":64,"age":17,"nat":"Republic of Ireland","club":"Waterford FC","cid":753,"league":"Premier Division","lvl":1,"jersey":40,"val":120000,"foot":"Right","wf":3,"sm":2,"rep":1,"h":175,"pace":61,"sho":26,"pas":29,"dri":31,"def":51,"phy":61,"img":"https://cdn.sofifa.net/players/077/509/26_120.png","tags":""},{"id":240838,"name":"B. Wade","full":"Bradley Calvin Wade","pos":"GK","fifa_pos":["GK"],"ovr":56,"pot":58,"age":24,"nat":"England","club":"Waterford FC","cid":753,"league":"Premier Division","lvl":1,"jersey":31,"val":140000,"foot":"Right","wf":2,"sm":1,"rep":1,"h":188,"pace":0,"sho":0,"pas":0,"dri":0,"def":0,"phy":0,"img":"https://cdn.sofifa.net/players/240/838/26_120.png","tags":""},{"id":273558,"name":"S. McMullan","full":"Stephen Desmond Soraghan McMullan","pos":"GK","fifa_pos":["GK"],"ovr":59,"pot":68,"age":20,"nat":"Northern Ireland","club":"Waterford FC","cid":753,"league":"Premier Division","lvl":1,"jersey":1,"val":425000,"foot":"Right","wf":2,"sm":1,"rep":1,"h":182,"pace":0,"sho":0,"pas":0,"dri":0,"def":0,"phy":0,"img":"https://cdn.sofifa.net/players/273/558/26_120.png","tags":""},{"id":75962,"name":"J. Healy","full":"Jason Healy","pos":"GK","fifa_pos":["GK"],"ovr":51,"pot":63,"age":19,"nat":"Republic of Ireland","club":"Waterford FC","cid":753,"league":"Premier Division","lvl":1,"jersey":25,"val":120000,"foot":"Right","wf":2,"sm":1,"rep":1,"h":188,"pace":0,"sho":0,"pas":0,"dri":0,"def":0,"phy":0,"img":"https://cdn.sofifa.net/players/075/962/26_120.png","tags":""}]